paconvert/__init__.py
paconvert/api_alias_mapping.json
paconvert/api_mapping.json
paconvert/api_matcher.py
paconvert/api_wildcard_mapping.json
paconvert/attribute_mapping.json
paconvert/base.py
paconvert/converter.py
paconvert/example_code.py
paconvert/global_var.py
paconvert/legacy.py
paconvert/main.py
paconvert/utils.py
paconvert/version.py
paconvert/transformer/__init__.py
paconvert/transformer/basic_transformer.py
paconvert/transformer/custom_op_transformer.py
paconvert/transformer/import_transformer.py
paconvert/transformer/tensor_requires_grad_transformer.py
paconvert-3.3.0.dist-info/LICENSE
paconvert-3.3.0.dist-info/METADATA
paconvert-3.3.0.dist-info/WHEEL
paconvert-3.3.0.dist-info/entry_points.txt
paconvert-3.3.0.dist-info/top_level.txt
paconvert-3.3.0.dist-info/RECORD
