Metadata-Version: 2.1
Name: paconvert
Version: 3.3.0
Summary: PaddlePaddle Code Convert Toolkits
Home-page: https://github.com/PaddlePaddle/PaConvert
Download-URL: https://github.com/PaddlePaddle/PaConvert
Author-email: Paddle-better@baidu.com
Maintainer: PaddlePaddle
Maintainer-email: Paddle-better@baidu.com
License: Apache Software License
Requires-Python: >=3.8
License-File: LICENSE
Requires-Dist: astor
Requires-Dist: black ==22.8.0
Requires-Dist: isort ==5.11.5
